blindbase/__init__.py
blindbase/__main__.py
blindbase/analysis.py
blindbase/app.py
blindbase/menu.py
blindbase/merge_games.py
blindbase/mll_trainer.py
blindbase/sounds_util.py
blindbase/commands/__init__.py
blindbase/commands/__main__.py
blindbase/commands/broadcasts.py
blindbase/commands/pgn.py
blindbase/commands/settings.py
blindbase/core/__init__.py
blindbase/core/engine.py
blindbase/core/navigator.py
blindbase/core/opening_tree.py
blindbase/core/pgn.py
blindbase/core/settings.py
blindbase/core/stream.py
blindbase/ui/__init__.py
blindbase/ui/accessibility.py
blindbase/ui/base.py
blindbase/ui/board.py
blindbase/ui/themes.py
blindbase/ui/utils.py
blindbase/ui/panels/analysis.py
blindbase/ui/panels/game_list.py
blindbase/ui/panels/opening_tree.py
blindbase/ui/panels/settings_menu.py
blindbase/ui/tests/__init__.py
blindbase/ui/views/__init__.py
blindbase/ui/views/game.py
blindbase/ui/views/pgn.py
blindbase/ui/views/training.py
blindbase/utils/board_desc.py
blindbase/utils/move_format.py
blindbase-0.13.0.dist-info/METADATA
blindbase-0.13.0.dist-info/WHEEL
blindbase-0.13.0.dist-info/entry_points.txt
blindbase-0.13.0.dist-info/top_level.txt
blindbase-0.13.0.dist-info/RECORD
