Metadata-Version: 2.4
Name: blindbase
Version: 0.13.0
Summary: Accessible CLI chess study tool with Stockfish analysis and  Lichess integration.
Author-email: Alexey Streltsov <iitshak@gmail.com>
License: MIT
Project-URL: Homepage, https://github.com/itshak/blind-base-cli
Keywords: chess,cli,accessibility,stockfish,blind,pgn
Classifier: License :: OSI Approved :: MIT License
Classifier: Programming Language :: Python :: 3
Classifier: Programming Language :: Python :: 3 :: Only
Classifier: Programming Language :: Python :: 3.9
Classifier: Programming Language :: Python :: 3.10
Classifier: Programming Language :: Python :: 3.11
Classifier: Programming Language :: Python :: 3.12
Classifier: Operating System :: MacOS
Classifier: Operating System :: Microsoft :: Windows
Classifier: Intended Audience :: End Users/Desktop
Classifier: Environment :: Console
Requires-Python: >=3.11
Requires-Dist: typer[all]>=0.9
Requires-Dist: rich>=13
Requires-Dist: python-chess>=1.999
Requires-Dist: requests>=2.26
Requires-Dist: pydantic>=1.10
Requires-Dist: pydantic-settings>=2.0
Requires-Dist: pygame>=2.5.2
Requires-Dist: tomlkit>=0.12
Provides-Extra: dev
Requires-Dist: pytest>=7.0; extra == "dev"
Requires-Dist: pytest-rich>=0.6; extra == "dev"
Requires-Dist: snapshottest>=0.6; extra == "dev"
Requires-Dist: mypy>=1.8; extra == "dev"
Requires-Dist: ruff>=0.4; extra == "dev"
